xarray_lmfit/__init__.py
xarray_lmfit/_io.py
xarray_lmfit/_utils.py
xarray_lmfit/modelfit.py
xarray_lmfit-0.5.4.dist-info/WHEEL
xarray_lmfit-0.5.4.dist-info/METADATA
xarray_lmfit-0.5.4.dist-info/RECORD
