Metadata-Version: 2.3
Name: xarray-lmfit
Version: 0.5.4
Summary: Fit lmfit models to xarray objects.
Keywords: lmfit,xarray,fitting
Author: Kimoon Han
Author-email: Kimoon Han <khan@kaist.ac.kr>
License:                     GNU GENERAL PUBLIC LICENSE
Classifier: Development Status :: 4 - Beta
Classifier: Intended Audience :: Science/Research
Classifier: Topic :: Scientific/Engineering
Classifier: License :: OSI Approved :: GNU General Public License v3 or later (GPLv3+)
Classifier: Programming Language :: Python :: 3.11
Classifier: Programming Language :: Python :: 3.12
Classifier: Programming Language :: Python :: 3.13
Classifier: Programming Language :: Python :: 3.14
Classifier: Operating System :: OS Independent
Requires-Dist: lazy-loader>=0.4
Requires-Dist: lmfit>=1.3.2
Requires-Dist: numpy>=1.26.0
Requires-Dist: xarray>=2024.10.0
Requires-Dist: tqdm>=4.66.2 ; extra == 'progress'
Requires-Python: >=3.11
Project-URL: Documentation, https://xarray-lmfit.readthedocs.io
Project-URL: Issues, https://github.com/kmnhan/xarray-lmfit/issues
Project-URL: Repository, https://github.com/kmnhan/xarray-lmfit.git
Provides-Extra: progress
